COPYING
MANIFEST.in
README.rst
bootstrap.py
buildout.cfg
setup.py
bob.spear.egg-info/PKG-INFO
bob.spear.egg-info/SOURCES.txt
bob.spear.egg-info/dependency_links.txt
bob.spear.egg-info/entry_points.txt
bob.spear.egg-info/not-zip-safe
bob.spear.egg-info/requires.txt
bob.spear.egg-info/top_level.txt
config/database/banca_audio_G.py
config/database/timit.py
config/database/voxforge.py
config/database/mobio/mobile0-female.py
config/database/mobio/mobile0-male.py
config/features/htk.py
config/features/lfcc_60.py
config/features/mfcc_60.py
config/features/spro.py
config/grid/demanding.py
config/grid/grid.py
config/grid/local.py
config/grid/para_training_local.py
config/grid/para_training_sge.py
config/grid/very_demanding.py
config/preprocessing/energy.py
config/preprocessing/energy_thr.py
config/preprocessing/external.py
config/preprocessing/mod_4hz.py
config/tools/isv/isv_256g_u50.py
config/tools/isv/isv_512g_u100.py
config/tools/isv/isv_512g_u200.py
config/tools/isv/isv_512g_u50.py
config/tools/isv/isv_8g_u20.py
config/tools/ivec/ivec_256g_t100_cosine.py
config/tools/ivec/ivec_256g_t100_plda.py
config/tools/ivec/ivec_512g_t400.py
config/tools/ivec/ivec_8g_t50.py
config/tools/jfa/jfa_256_v10_u10.py
config/tools/jfa/jfa_256_v5_u10.py
config/tools/jfa/jfa_8_v_5_u_5.py
config/tools/ubm_gmm/ubm_gmm_256G.py
config/tools/ubm_gmm/ubm_gmm_512G.py
config/tools/ubm_gmm/ubm_gmm_512G_regular_scoring.py
config/tools/ubm_gmm/ubm_gmm_8G.py
icassp_2014/reproduce_results.sh
protocols/readme.txt
protocols/banca/G/dev/for_models.lst
protocols/banca/G/dev/for_scores.lst
protocols/banca/G/eval/for_models.lst
protocols/banca/G/eval/for_scores.lst
protocols/banca/G/norm/train_optional_world_1.lst
protocols/banca/G/norm/train_optional_world_2.lst
protocols/banca/G/norm/train_world.lst
protocols/mobio/mobile0-female/dev/for_models.lst
protocols/mobio/mobile0-female/dev/for_scores.lst
protocols/mobio/mobile0-female/dev/for_tnorm.lst
protocols/mobio/mobile0-female/dev/for_znorm.lst
protocols/mobio/mobile0-female/eval/for_models.lst
protocols/mobio/mobile0-female/eval/for_scores.lst
protocols/mobio/mobile0-female/eval/for_tnorm.lst
protocols/mobio/mobile0-female/eval/for_znorm.lst
