Metadata-Version: 1.1
Name: bob.spear
Version: 1.1.8
Summary: Speaker recognition toolkit
Home-page: https://pypi.python.org/pypi/bob.spear
Author: Elie Khoury
Author-email: Elie.Khoury@idiap.ch
License: GPLv3
Keywords: Speaker Recognition,Speaker verification,Gaussian Mixture Model,ISV,UBM-GMM,I-Vector,Audio processing,NIST SRE 2012,Database
Platform: UNKNOWN
Classifier: Development Status :: 4 - Beta
Classifier: Intended Audience :: Developers
Classifier: License :: OSI Approved :: GNU General Public License v3 (GPLv3)
Classifier: Natural Language :: English
Classifier: Programming Language :: Python
Classifier: Topic :: Scientific/Engineering :: Artificial Intelligence
